README.md
setup.py
spb_apps/__init__.py
spb_apps/apps.py
spb_apps/superb_curate.py
spb_apps/superb_label.py
spb_apps/curate/__init__.py
spb_apps/curate/utils.py
spb_apps/label/__init__.py
spb_apps/model/__init__.py
spb_apps/model/dynamic_module_utils.py
spb_apps/model/feature_extraction_utils.py
spb_apps/model/image_processing_base.py
spb_apps/model/image_processing_utils.py
spb_apps/model/image_processing_utils_fast.py
spb_apps/model/image_transforms.py
spb_apps/model/image_utils.py
spb_apps/model/deta/__init__.py
spb_apps/model/deta/image_processor_deta_fast.py
spb_apps/model/detr/__init__.py
spb_apps/model/detr/image_processor_detr.py
spb_apps/model/detr/image_processor_detr_fast.py
spb_apps/model/utils/__init__.py
spb_apps/model/utils/backbone_utils.py
spb_apps/model/utils/bitsandbytes.py
spb_apps/model/utils/chat_template_utils.py
spb_apps/model/utils/constants.py
spb_apps/model/utils/deprecation.py
spb_apps/model/utils/doc.py
spb_apps/model/utils/dummy_detectron2_objects.py
spb_apps/model/utils/dummy_essentia_and_librosa_and_pretty_midi_and_scipy_and_torch_objects.py
spb_apps/model/utils/dummy_flax_objects.py
spb_apps/model/utils/dummy_keras_nlp_objects.py
spb_apps/model/utils/dummy_music_objects.py
spb_apps/model/utils/dummy_pt_objects.py
spb_apps/model/utils/dummy_sentencepiece_and_tokenizers_objects.py
spb_apps/model/utils/dummy_sentencepiece_objects.py
spb_apps/model/utils/dummy_speech_objects.py
spb_apps/model/utils/dummy_tensorflow_text_objects.py
spb_apps/model/utils/dummy_tf_objects.py
spb_apps/model/utils/dummy_timm_and_torchvision_objects.py
spb_apps/model/utils/dummy_tokenizers_objects.py
spb_apps/model/utils/dummy_torchaudio_objects.py
spb_apps/model/utils/dummy_torchvision_objects.py
spb_apps/model/utils/dummy_vision_objects.py
spb_apps/model/utils/fx.py
spb_apps/model/utils/generic.py
spb_apps/model/utils/hp_naming.py
spb_apps/model/utils/hub.py
spb_apps/model/utils/import_utils.py
spb_apps/model/utils/logging.py
superb_ai_apps.egg-info/PKG-INFO
superb_ai_apps.egg-info/SOURCES.txt
superb_ai_apps.egg-info/dependency_links.txt
superb_ai_apps.egg-info/requires.txt
superb_ai_apps.egg-info/top_level.txt