Metadata-Version: 2.1
Name: superb-ai-apps
Version: 0.0.26
Summary: Python Package for Superb-AI Apps
Home-page: UNKNOWN
License: UNKNOWN
Platform: UNKNOWN
Provides-Extra: all
